Metadata-Version: 2.1
Name: uav-collision-avoidance
Version: 1.0.0
Summary: UAV collision avoidance simulation
Author-email: mldxo <miloszmaculewicz@gmail.com>
Project-URL: Homepage, https://github.com/mldxo/uav-collision-avoidance
Project-URL: Issues, https://github.com/mldxo/uav-collision-avoidance/issues
Classifier: Programming Language :: Python :: 3
Classifier: License :: OSI Approved :: MIT License
Classifier: Operating System :: OS Independent
Requires-Python: >=3.11
License-File: LICENSE
Requires-Dist: setuptools
Requires-Dist: wheel
Requires-Dist: twine >=5.0.0
Requires-Dist: toml >=0.10.2
Requires-Dist: build >=1.2.1
Requires-Dist: pyinstaller >=6.6.0
Requires-Dist: PySide6 ==6.7.0
Requires-Dist: numpy >=1.26.4
Requires-Dist: pandas >=2.2.2
Requires-Dist: matplotlib >=3.8.4
Requires-Dist: pytest >=8.1.1
Requires-Dist: screeninfo >=0.8.1
Requires-Dist: pylint >=3.2.0
